PLL_Lib/__init__.py
PLL_Lib/arduino.py
PLL_Lib/arduinoerrorhelp.py
PLL_Lib/constants.py
PLL_Lib/device.py
PLL_Lib/display.py
PLL_Lib/errors.py
PLL_Lib/library.py
PLL_Lib/picoerrorhelp.py
PLL_Lib/picoscope.py
PLL_Lib/ps2000.dll
PLL_Lib/ps2000.lib
PLL_Lib/ps2000.py
PLL_Lib-1.0.1.dist-info/LICENSE.md
PLL_Lib-1.0.1.dist-info/METADATA
PLL_Lib-1.0.1.dist-info/WHEEL
PLL_Lib-1.0.1.dist-info/top_level.txt
PLL_Lib-1.0.1.dist-info/RECORD
