Metadata-Version: 2.1
Name: PLL-Lib
Version: 1.0.1
Summary: Package for Cambridge Part II Experiment Phase Locked Loops
Home-page: https://github.com/Cicuta-Group/PLL_lib_project
Author: Stasiu Wolanski
Author-email: sw902@cam.ac.uk
License: UNKNOWN
Project-URL: Bug Tracker, https://github.com/Cicuta-Group/PLL_lib_project/issues
Platform: UNKNOWN
Classifier: Programming Language :: Python :: 3
Classifier: License :: OSI Approved :: MIT License
Classifier: Operating System :: Microsoft :: Windows
Requires-Python: >=3.6
Requires-Dist: pyglet (==1.5.*)
Requires-Dist: numpy (>=1.22.0)
Requires-Dist: pyserial (>=3.5)
